credkit/__init__.py
credkit/behavior/__init__.py
credkit/behavior/adjustments.py
credkit/behavior/default.py
credkit/behavior/loss.py
credkit/behavior/prepayment.py
credkit/cashflow/__init__.py
credkit/cashflow/cashflow.py
credkit/cashflow/discount.py
credkit/cashflow/schedule.py
credkit/instruments/__init__.py
credkit/instruments/amortization.py
credkit/instruments/loan.py
credkit/money/__init__.py
credkit/money/currency.py
credkit/money/money.py
credkit/money/rate.py
credkit/money/spread.py
credkit/portfolio/__init__.py
credkit/portfolio/portfolio.py
credkit/portfolio/repline.py
credkit/py.typed
credkit/temporal/__init__.py
credkit/temporal/calendar.py
credkit/temporal/daycount.py
credkit/temporal/frequency.py
credkit/temporal/period.py
credkit-0.5.1.dist-info/WHEEL
credkit-0.5.1.dist-info/METADATA
credkit-0.5.1.dist-info/RECORD
