Metadata-Version: 2.3
Name: credkit
Version: 0.5.1
Summary: An open credit modeling tool kit
Author: jt-hill
Author-email: jt-hill <13084189+jt-hill@users.noreply.github.com>
License: AGPL-3.0-only
Requires-Dist: pyxirr>=0.10
Requires-Python: >=3.13
